miyao/__init__.py
miyao/_config.py
miyao/_vault.py
miyao/cli.py
miyao/py.typed
miyao-0.2.0.dist-info/METADATA
miyao-0.2.0.dist-info/WHEEL
miyao-0.2.0.dist-info/entry_points.txt
miyao-0.2.0.dist-info/RECORD
